{
    "name": "Birch Forest",
    "color": "#B06F27",
    "rarity": 2,
    "vanillaDerivative": "BIRCH_FOREST",
    "customDerivitives": [
        {
            "id": "birch_forest",
            "waterColor": "#48abf7",
            "downfallType": "rain"
        }
    ],
    "generators": [
        {
            "min": 5,
            "max": 9,
            "generator": "meadows"
        },
        {
            "min": 7,
            "max": 12,
            "generator": "meadows"
        },
        {
            "min": -12,
            "max": -5,
            "generator": "mountain"
        }
    ],
    "biomeZoom": 3,
    "wall": {
        "style": {
            "style": "STATIC"
        },
        "slopeCondition": {
            "minimumSlope": 3
        },
        "palette": [
            {
                "block": "minecraft:stone",
                "weight": 3
            },
            {
                "block": "minecraft:andesite"
            }
        ]
    },
    "layers": [
        {
            "style": {
                "style": "STATIC"
            },
            "zoom": 0.75,
            "palette": [
                {
                    "block": "minecraft:grass_block"
                }
            ]
        },
        {
            "minHeight": 2,
            "maxHeight": 4,
            "palette": [
                {
                    "block": "minecraft:dirt"
                }
            ]
        },
        {
            "style": {
                "style": "CELLULAR"
            },
            "zoom": 0.18,
            "palette": [
                {
                    "block": "minecraft:andesite",
                    "weight": 3
                },
                {
                    "block": "minecraft:granite",
                    "weight": 1
                },
                {
                    "block": "minecraft:diorite",
                    "weight": 1
                },
                {
                    "block": "minecraft:stone",
                    "weight": 16
                }
            ]
        }
    ],
    "objects": [
        {
            "translate": {
                "y": 1
            },
            "density": 4,
            "chance": 1,
            "place": [
                "trees/birch/forest/1",
                "trees/birch/forest/2",
                "trees/birch/forest/3",
                "trees/birch/forest/4",
                "trees/birch/forest/5",
                "trees/birch/forest/7",
                "trees/birch/forest/9",
                "trees/birch/forest/10"
            ]
        },
        {
            "translate": {
                "y": 1
            },
            "density": 2,
            "chance": 0.25,
            "place": [
                "trees/birch/forest/6",
                "trees/birch/forest/8"
            ]
        },
        {
            "translate": {
                "y": 1
            },
            "density": 2,
            "chance": 0.45,
            "place": [
                "trees/birch/forest/bushes/1",
                "trees/birch/forest/bushes/2",
                "trees/birch/forest/bushes/3",
                "trees/birch/forest/bushes/4",
                "trees/birch/forest/bushes/5",
                "trees/birch/forest/bushes/6",
                "trees/birch/forest/bushes/7"
            ]
        }
    ],
    "decorators": [
        {
            "style": {
                "style": "STATIC"
            },
            "zoom": 0.17,
            "chance": 0.004,
            "palette": [
                {
                    "block": "minecraft:dandelion"
                },
                {
                    "block": "minecraft:poppy"
                },
                {
                    "block": "minecraft:blue_orchid"
                },
                {
                    "block": "minecraft:allium"
                },
                {
                    "block": "minecraft:azure_bluet"
                },
                {
                    "block": "minecraft:red_tulip"
                },
                {
                    "block": "minecraft:orange_tulip"
                },
                {
                    "block": "minecraft:white_tulip"
                },
                {
                    "block": "minecraft:pink_tulip"
                },
                {
                    "block": "minecraft:oxeye_daisy"
                },
                {
                    "block": "minecraft:cornflower"
                },
                {
                    "block": "minecraft:lily_of_the_valley"
                },
                {
                    "block": "minecraft:lilac"
                },
                {
                    "block": "minecraft:rose_bush"
                },
                {
                    "block": "minecraft:sunflower"
                },
                {
                    "block": "extracraft:blue_hydrangea_placed"
                },
                {
                    "block": "extracraft:burning_blossom_placed"
                },
                {
                    "block": "extracraft:lavender_placed"
                },
                {
                    "block": "extracraft:lavender_alt_placed"
                },
                {
                    "block": "extracraft:orange_cosmos_placed"
                },
                {
                    "block": "extracraft:pink_daffodil_placed"
                },
                {
                    "block": "extracraft:violet_placed"
                },
                {
                    "block": "extracraft:goldenrod_placed"
                },
                {
                    "block": "extracraft:white_lavender_placed"
                },
                {
                    "block": "extracraft:white_lavender_alt_placed"
                }
            ]
        },
        {
            "chance": 0.001,
            "variance": {
                "style": "STATIC"
            },
            "zoom": 0.3,
            "palette": [
                {
                    "block": "minecraft:dead_bush"
                }
            ],
            "style": {
                "style": "STATIC"
            }
        },
        {
            "chance": 0.3,
            "variance": {
                "style": "STATIC"
            },
            "zoom": 0.3,
            "palette": [
                {
                    "block": "minecraft:short_grass"
                }
            ],
            "style": {
                "style": "STATIC"
            }
        },
        {
            "chance": 0.01,
            "variance": {
                "style": "STATIC"
            },
            "zoom": 0.3,
            "palette": [
                {
                    "block": "minecraft:tall_grass"
                }
            ],
            "style": {
                "style": "STATIC"
            }
        }
    ]
}
